setup.py
utpl/__init__.py
utpl/ensayos/__init__.py
utpl/ensayos/bayrak_sheikh.py
utpl/ensayos/momento_curvatura.py
utpl/ensayos/tanaka_park.py
utpl/ensayos/wehbe.py
utpl/modelos/__init__.py
utpl/modelos/acelerograma.py
utpl/modelos/amortiguador.py
utpl/modelos/carga.py
utpl/modelos/carga_distribuida.py
utpl/modelos/columna_aislador.py
utpl/modelos/columna_perfil.py
utpl/modelos/desplazamiento.py
utpl/modelos/excitacion_sinuidal.py
utpl/tests/__init__.py
utpl/tests/tests.py
utpl_modelos_columnas.egg-info/PKG-INFO
utpl_modelos_columnas.egg-info/SOURCES.txt
utpl_modelos_columnas.egg-info/dependency_links.txt
utpl_modelos_columnas.egg-info/requires.txt
utpl_modelos_columnas.egg-info/top_level.txt