Metadata-Version: 2.1
Name: utpl-modelos-columnas
Version: 4.0
Summary: Modelos de Columnas- Tesis de Grado
Home-page: https://github.com/ravalenciaochoa/utpl
Author: Ronald Valencia
Author-email: ravalencia2@utpl.edu.ec
License: UNKNOWN
Platform: UNKNOWN
Classifier: Development Status :: 3 - Alpha
Classifier: Topic :: Utilities
Classifier: License :: OSI Approved :: GNU General Public License (GPL)
